getml/VERSION
getml/__init__.py
getml/communication.py
getml/constants.py
getml/cross_validation.py
getml/exceptions.py
getml/helpers.py
getml/log.py
getml/spark.py
getml/version.py
getml/data/__init__.py
getml/data/access.py
getml/data/concat.py
getml/data/container.py
getml/data/data_frame.py
getml/data/data_model.py
getml/data/diagram.py
getml/data/helpers.py
getml/data/helpers2.py
getml/data/load_container.py
getml/data/placeholder.py
getml/data/relationship.py
getml/data/staging.py
getml/data/star_schema.py
getml/data/subset.py
getml/data/time.py
getml/data/time_series.py
getml/data/view.py
getml/data/_io/arrow.py
getml/data/_io/csv.py
getml/data/_io/parquet.py
getml/data/columns/__init__.py
getml/data/columns/aggregation.py
getml/data/columns/collect_footer_data.py
getml/data/columns/column.py
getml/data/columns/columns.py
getml/data/columns/constants.py
getml/data/columns/format.py
getml/data/columns/from_value.py
getml/data/columns/get_scalar.py
getml/data/columns/last_change.py
getml/data/columns/last_change_from_col.py
getml/data/columns/length.py
getml/data/columns/length_property.py
getml/data/columns/make_iter.py
getml/data/columns/parse.py
getml/data/columns/random.py
getml/data/columns/repr.py
getml/data/columns/repr_html.py
getml/data/columns/subroles.py
getml/data/columns/to_arrow.py
getml/data/columns/to_numpy.py
getml/data/columns/unique.py
getml/data/columns/unit.py
getml/data/roles/__init__.py
getml/data/roles/container.py
getml/data/roles/roles.py
getml/data/roles/sets.py
getml/data/roles/types.py
getml/data/split/__init__.py
getml/data/split/concat.py
getml/data/split/random.py
getml/data/split/time.py
getml/data/subroles/__init__.py
getml/data/subroles/exclude.py
getml/data/subroles/include.py
getml/data/subroles/only.py
getml/data/subroles/sets.py
getml/data/subroles/types.py
getml/database/__init__.py
getml/database/connect_bigquery.py
getml/database/connect_duckdb.py
getml/database/connect_greenplum.py
getml/database/connect_hana.py
getml-1.5.1.dist-info/METADATA
getml-1.5.1.dist-info/WHEEL
getml-1.5.1.dist-info/licenses/LICENSE
getml-1.5.1.dist-info/RECORD
